LICENSE
MANIFEST.in
README.md
requirements.txt
setup.py
mysqlmapper/__init__.py
mysqlmapper/engine.py
mysqlmapper/facade.py
mysqlmapper.egg-info/PKG-INFO
mysqlmapper.egg-info/SOURCES.txt
mysqlmapper.egg-info/dependency_links.txt
mysqlmapper.egg-info/not-zip-safe
mysqlmapper.egg-info/requires.txt
mysqlmapper.egg-info/top_level.txt
mysqlmapper/manager/__init__.py
mysqlmapper/manager/mvc/__init__.py
mysqlmapper/manager/mvc/dao.py
mysqlmapper/manager/mvc/holder.py
mysqlmapper/manager/mvc/info.py
mysqlmapper/manager/mvc/mapper.py
mysqlmapper/manager/mvc/service.py
mysqlmapper/manager/session/__init__.py
mysqlmapper/manager/session/sql_session_factory.py
mysqlmapper/manager/session/decorators/__init__.py
mysqlmapper/manager/session/decorators/sql_session.py